bigquery_validator/__init__.py
bigquery_validator/__main__.py
bigquery_validator/bigquery_result.py
bigquery_validator/bigquery_validator.py
bigquery_validator/bigquery_validator_util.py
bigquery_validator/tests/__init__.py
bigquery_validator/tests/baseball_data_validation_test.py
bigquery_validator/tests/bigquery_result_test.py
bigquery_validator/tests/bigquery_validator_test.py
config/__init__.py
config/config.py
python_bigquery_validator-1.0.1.dist-info/LICENSE
python_bigquery_validator-1.0.1.dist-info/METADATA
python_bigquery_validator-1.0.1.dist-info/WHEEL
python_bigquery_validator-1.0.1.dist-info/top_level.txt
python_bigquery_validator-1.0.1.dist-info/RECORD
