Metadata-Version: 2.1
Name: python-bigquery-validator
Version: 1.0.1
Summary: Python module for validating BigQuery sql queries with support for Jinja templated variables
Home-page: https://github.com/tunnelWithAC/python-bigquery-validator
Author: Conall Daly
Author-email: conalldalydev@gmail.com
Classifier: Programming Language :: Python :: 3
Classifier: License :: OSI Approved :: MIT License
Classifier: Operating System :: OS Independent
Requires-Python: >=3.7
License-File: LICENSE
Requires-Dist: google-cloud-bigquery
Requires-Dist: Jinja2
